daystrom/__init__.py
daystrom/components/__init__.py
daystrom/components/base.py
daystrom/components/instructor.py
daystrom/components/openai/__init__.py
daystrom/components/openai/chat_completions.py
daystrom/components/openrouter/__init__.py
daystrom/components/openrouter/chat.py
daystrom/exceptions/__init__.py
daystrom/exceptions/components.py
daystrom/logging.py
daystrom/providers.py
daystrom-0.1.2.dist-info/licenses/LICENSE.md
daystrom-0.1.2.dist-info/WHEEL
daystrom-0.1.2.dist-info/METADATA
daystrom-0.1.2.dist-info/RECORD
