Metadata-Version: 2.4
Name: daystrom
Version: 0.1.2
Summary: Daystrom is an agent framework for easily building workflows
Author: Lucas Teixeira
Author-email: Lucas Teixeira <lemetechnical@gmail.com>
License-Expression: LicenseRef-FSL-1.1-MIT
License-File: LICENSE.md
Requires-Dist: docstring-parser>=0.17.0
Requires-Dist: httpx>=0.28.1
Requires-Dist: instructor>=1.13.0
Requires-Dist: openai>=2.13.0
Requires-Dist: openrouter>=0.1.1
Requires-Python: >=3.12
Project-URL: Homepage, https://github.com/prilosac/daystrom
